llm_ide_rules/__init__.py
llm_ide_rules/__main__.py
llm_ide_rules/commands/delete.py
llm_ide_rules/commands/download.py
llm_ide_rules/commands/explode.py
llm_ide_rules/commands/implode.py
llm_ide_rules/constants.py
llm_ide_rules/sections.json
llm_ide_rules-0.4.0.dist-info/WHEEL
llm_ide_rules-0.4.0.dist-info/entry_points.txt
llm_ide_rules-0.4.0.dist-info/METADATA
llm_ide_rules-0.4.0.dist-info/RECORD
