Metadata-Version: 2.3
Name: llm-ide-rules
Version: 0.4.0
Summary: CLI tool for managing LLM IDE prompts and rules
Keywords: llm,ide,prompts,cursor,copilot
Author: Michael Bianco
Author-email: Michael Bianco <mike@mikebian.co>
Requires-Dist: typer>=0.9.0
Requires-Dist: structlog>=23.2.0
Requires-Dist: requests>=2.25.0
Requires-Python: >=3.9
Project-URL: Repository, https://github.com/iloveitaly/llm-ide-rules
